LICENSE.txt
README.md
setup.cfg
setup.py
tk_async_image/__init__.py
tk_async_image/tk_async_image.py
tk_async_image.egg-info/PKG-INFO
tk_async_image.egg-info/SOURCES.txt
tk_async_image.egg-info/dependency_links.txt
tk_async_image.egg-info/top_level.txt