Metadata-Version: 1.0
Name: tk-async-image
Version: 1.1.0
Summary: Async Image for tkinter
Home-page: https://github.com/denilson-dxt/TkAsyncImage
Author: Denilson Tivane
Author-email: denilsontivane@gmail.com
License: MIT
Keywords: async image for tk
Platform: UNKNOWN
